audiopackage/__init__.py
audiopackage-0.1.dist-info/METADATA
audiopackage-0.1.dist-info/WHEEL
audiopackage-0.1.dist-info/top_level.txt
audiopackage-0.1.dist-info/RECORD
