Metadata-Version: 2.1
Name: audiopackage
Version: 0.1
Summary: Covert autio into text
Author: junaid
Author-email: junaid.sharif104@gmail.com
